wsdiscovery/__init__.py
wsdiscovery/asynch.py
wsdiscovery/cmdline.py
wsdiscovery/daemon.py
wsdiscovery/discovery.py
wsdiscovery/envelope.py
wsdiscovery/interfaces.py
wsdiscovery/message.py
wsdiscovery/namespaces.py
wsdiscovery/publishing.py
wsdiscovery/qname.py
wsdiscovery/scope.py
wsdiscovery/service.py
wsdiscovery/threaded.py
wsdiscovery/udp.py
wsdiscovery/uri.py
wsdiscovery/util.py
wsdiscovery/actions/__init__.py
wsdiscovery/actions/bye.py
wsdiscovery/actions/hello.py
wsdiscovery/actions/probe.py
wsdiscovery/actions/probematch.py
wsdiscovery/actions/resolve.py
wsdiscovery/actions/resolvematch.py
WSDiscovery-2.0.0.dist-info/LICENSE
WSDiscovery-2.0.0.dist-info/METADATA
WSDiscovery-2.0.0.dist-info/WHEEL
WSDiscovery-2.0.0.dist-info/entry_points.txt
WSDiscovery-2.0.0.dist-info/top_level.txt
WSDiscovery-2.0.0.dist-info/RECORD
